ciscoreputation/__about__.py
ciscoreputation/__init__.py
ciscoreputation/ciscoreputation.py
ciscoreputation-2.1.4.dist-info/LICENSE
ciscoreputation-2.1.4.dist-info/METADATA
ciscoreputation-2.1.4.dist-info/WHEEL
ciscoreputation-2.1.4.dist-info/entry_points.txt
ciscoreputation-2.1.4.dist-info/top_level.txt
ciscoreputation-2.1.4.dist-info/RECORD
