Metadata-Version: 2.1
Name: ciscoreputation
Version: 2.1.4
Summary: Get the Cisco's senderbase.org reputation for a hostname or ip address
Home-page: https://github.com/cescobarresi/ciscoreputation
Author: Francesco Barresi
Author-email: francescobarresi@bbfactory.it
License: MIT
Platform: UNKNOWN
Classifier: Development Status :: 4 - Beta
Classifier: Environment :: Console
Classifier: Intended Audience :: System Administrators
Classifier: License :: OSI Approved :: MIT License
Classifier: Programming Language :: Python :: 2.7
Classifier: Programming Language :: Python :: 3.7
Classifier: Natural Language :: English
Classifier: Operating System :: POSIX :: Linux
Requires-Dist: docopt
Requires-Dist: requests
